Metadata-Version: 2.1
Name: Autor
Version: 0.0.3
Summary: An application that helps you with your Hangzhou Safety Education Tasks
Home-page: https://github.com/7emotions/Autor
Author: Lorenzo Feng
Author-email: paradise_c@qq.com
License: MIT Licence
Keywords: pip,Autor
Platform: any
